ycls/__init__.py
ycls/ycls.py
ycls-1.0.7.dist-info/METADATA
ycls-1.0.7.dist-info/WHEEL
ycls-1.0.7.dist-info/entry_points.txt
ycls-1.0.7.dist-info/top_level.txt
ycls-1.0.7.dist-info/RECORD
