Metadata-Version: 2.1
Name: ycls
Version: 1.0.7
Summary: YCLS is a Python module for calculating loudness metrics for audio (or video) files, particularly aimed at determining the loudness level suitable for YouTube content.
Requires-Dist: r128gain
Requires-Dist: typer
